aiorpc/__init__.py
aiorpc/rmq.py
aiorpc/utils.py
OGAIO_RMQ-0.1.0.dist-info/LICENSE
OGAIO_RMQ-0.1.0.dist-info/METADATA
OGAIO_RMQ-0.1.0.dist-info/WHEEL
OGAIO_RMQ-0.1.0.dist-info/top_level.txt
OGAIO_RMQ-0.1.0.dist-info/RECORD
